Workbook

Sheet customers
A1: Customer_id | B1: First_name | C1: Last_name | D1: Phone | E1: Email | F1: Street | G1: City | H1: State | I1: Zip_code
A2: 1 | B2: Debra | C2: Burks | D2: NA | E2: debra.burks@yahoo.com | F2: 9273 Thorne Ave. | G2: Orchard Park | H2: NY | I2: 14127
A3: 2 | B3: Kasha | C3: Todd | D3: NA | E3: kasha.todd@yahoo.com | F3: 910 Vine Street | G3: Campbell | H3: CA | I3: 95008
A4: 3 | B4: Tameka | C4: Fisher | D4: NA | E4: tameka.fisher@aol.com | F4: 769C Honey Creek St. | G4: Redondo Beach | H4: CA | I4: 90278
A5: 4 | B5: Daryl | C5: Spence | D5: NA | E5: daryl.spence@aol.com | F5: 988 Pearl Lane | G5: Uniondale | H5: NY | I5: 11553
A6: 5 | B6: Charolette | C6: Rice | D6: (916) 381-6003 | E6: charolette.rice@msn.com | F6: 107 River Dr. | G6: Sacramento | H6: CA | I6: 95820
A7: 6 | B7: Lyndsey | C7: Bean | D7: NA | E7: lyndsey.bean@hotmail.com | F7: 769 West Road | G7: Fairport | H7: NY | I7: 14450
A8: 7 | B8: Latasha | C8: Hays | D8: (716) 986-3359 | E8: latasha.hays@hotmail.com | F8: 7014 Manor Station Rd. | G8: Buffalo | H8: NY | I8: 14215
A9: 8 | B9: Jacquline | C9: Duncan | D9: NA | E9: jacquline.duncan@yahoo.com | F9: 15 Brown St. | G9: Jackson Heights | H9: NY | I9: 11372
A10: 9 | B10: Genoveva | C10: Baldwin | D10: NA | E10: genoveva.baldwin@msn.com | F10: 8550 Spruce Drive | G10: Port Washington | H10: NY | I10: 11050
A11: 10 | B11: Pamelia | C11: Newman | D11: NA | E11: pamelia.newman@gmail.com | F11: 476 Chestnut Ave. | G11: Monroe | H11: NY | I11: 10950
A12: 11 | B12: Deshawn | C12: Mendoza | D12: NA | E12: deshawn.mendoza@yahoo.com | F12: 8790 Cobblestone Street | G12: Monsey | H12: NY | I12: 10952
A13: 12 | B13: Robby | C13: Sykes | D13: (516) 583-7761 | E13: robby.sykes@hotmail.com | F13: 486 Rock Maple Street | G13: Hempstead | H13: NY | I13: 11550
... A1446: 1445 | B1446: Ester | C1446: Acevedo | D1446: NA | E1446: ester.acevedo@gmail.com | F1446: 671 Miles Court | G1446: San Lorenzo | H1446: CA | I1446: 94580

Sheet stores
A1: Store_id | B1: Store_name | C1: Phone | D1: Email | E1: Street | F1: City | G1: State | H1: Zip_code
A2: 1 | B2: Santa Cruz Bikes | C2: (831) 476-4321 | D2: santacruz@bikes.shop | E2: 3700 Portola Drive | F2: Santa Cruz | G2: CA | H2: 95060
A3: 2 | B3: Baldwin Bikes | C3: (516) 379-8888 | D3: baldwin@bikes.shop | E3: 4200 Chestnut Lane | F3: Baldwin | G3: NY | H3: 11432
A4: 3 | B4: Rowlett Bikes | C4: (972) 530-5555 | D4: rowlett@bikes.shop | E4: 8000 Fairway Avenue | F4: Rowlett | G4: TX | H4: 75088

Sheet stocks
A1: Store_id | B1: Product_id | C1: Quantity
A2: 1 | B2: 1 | C2: 27
A3: 1 | B3: 2 | C3: 5
A4: 1 | B4: 3 | C4: 6
A5: 1 | B5: 4 | C5: 23
A6: 1 | B6: 5 | C6: 22
A7: 1 | B7: 6 | C7: 0
A8: 1 | B8: 7 | C8: 8
A9: 1 | B9: 8 | C9: 0
A10: 1 | B10: 9 | C10: 11
A11: 1 | B11: 10 | C11: 15
A12: 1 | B12: 11 | C12: 8
A13: 1 | B13: 12 | C13: 16
... A940: 3 | B940: 313 | C940: 0

Sheet staffs
A1: Staff_id | B1: First_name | C1: Last_name | D1: Email | E1: Phone | F1: Active | G1: Store_id | H1: Manager_id
A2: 1 | B2: Fabiola | C2: Jackson | D2: fabiola.jackson@bikes.shop | E2: (831) 555-5554 | F2: 1 | G2: 1 | H2: NA
A3: 2 | B3: Mireya | C3: Copeland | D3: mireya.copeland@bikes.shop | E3: (831) 555-5555 | F3: 1 | G3: 1 | H3: 1
A4: 3 | B4: Genna | C4: Serrano | D4: genna.serrano@bikes.shop | E4: (831) 555-5556 | F4: 1 | G4: 1 | H4: 2
A5: 4 | B5: Virgie | C5: Wiggins | D5: virgie.wiggins@bikes.shop | E5: (831) 555-5557 | F5: 1 | G5: 1 | H5: 2
A6: 5 | B6: Jannette | C6: David | D6: jannette.david@bikes.shop | E6: (516) 379-4444 | F6: 1 | G6: 2 | H6: 1
A7: 6 | B7: Marcelene | C7: Boyer | D7: marcelene.boyer@bikes.shop | E7: (516) 379-4445 | F7: 1 | G7: 2 | H7: 5
A8: 7 | B8: Venita | C8: Daniel | D8: venita.daniel@bikes.shop | E8: (516) 379-4446 | F8: 1 | G8: 2 | H8: 5
A9: 8 | B9: Kali | C9: Vargas | D9: kali.vargas@bikes.shop | E9: (972) 530-5555 | F9: 1 | G9: 3 | H9: 1
A10: 9 | B10: Layla | C10: Terrell | D10: layla.terrell@bikes.shop | E10: (972) 530-5556 | F10: 1 | G10: 3 | H10: 7
A11: 10 | B11: Bernardine | C11: Houston | D11: bernardine.houston@bikes.shop | E11: (972) 530-5557 | F11: 1 | G11: 3 | H11: 7

Sheet products
A1: Product_id | B1: Product_name | C1: Brand_id | D1: Category_id | E1: Model_year | F1: List_price
A2: 1 | B2: Trek 820 - 2016 | C2: 9 | D2: 6 | E2: 2016 | F2: 379.99
A3: 2 | B3: Ritchey Timberwolf Frameset - 2016 | C3: 5 | D3: 6 | E3: 2016 | F3: 749.99
A4: 3 | B4: Surly Wednesday Frameset - 2016 | C4: 8 | D4: 6 | E4: 2016 | F4: 999.99
A5: 4 | B5: Trek Fuel EX 8 29 - 2016 | C5: 9 | D5: 6 | E5: 2016 | F5: 2899.99
A6: 5 | B6: Heller Shagamaw Frame - 2016 | C6: 3 | D6: 6 | E6: 2016 | F6: 1320.99
A7: 6 | B7: Surly Ice Cream Truck Frameset - 2016 | C7: 8 | D7: 6 | E7: 2016 | F7: 469.99
A8: 7 | B8: Trek Slash 8 27.5 - 2016 | C8: 9 | D8: 6 | E8: 2016 | F8: 3999.99
A9: 8 | B9: Trek Remedy 29 Carbon Frameset - 2016 | C9: 9 | D9: 6 | E9: 2016 | F9: 1799.99
A10: 9 | B10: Trek Conduit+ - 2016 | C10: 9 | D10: 5 | E10: 2016 | F10: 2999.99
A11: 10 | B11: Surly Straggler - 2016 | C11: 8 | D11: 4 | E11: 2016 | F11: 1549
A12: 11 | B12: Surly Straggler 650b - 2016 | C12: 8 | D12: 4 | E12: 2016 | F12: 1680.99
A13: 12 | B13: Electra Townie Original 21D - 2016 | C13: 1 | D13: 3 | E13: 2016 | F13: 549.99
... A322: 321 | B322: Trek Checkpoint ALR Frameset - 2019 | C322: 9 | D322: 7 | E322: 2019 | F322: 3199.99

Sheet orders
A1: Order_id | B1: Customer_id | C1: Order_status | D1: Order_date | E1: Required_date | F1: Shipped_date | G1: Store_id | H1: Staff_id | J1: Order_state
A2: 1 | B2: 259 | C2: 4 | D2: 42370 | E2: 42372 | F2: 03-01-2016 | G2: 1 | H2: 2 | J2: {=_xlfn.IFS(C2=4,"Delivered",C2=3,"Shipped",C2=2,"Pending",C2=1,"Ordered")} -> Delivered
A3: 2 | B3: 1212 | C3: 4 | D3: 42370 | E3: 42373 | F3: 03-01-2016 | G3: 2 | H3: 6 | J3: {=_xlfn.IFS(C3=4,"Delivered",C3=3,"Shipped",C3=2,"Pending",C3=1,"Ordered")} -> Delivered
A4: 3 | B4: 523 | C4: 4 | D4: 42371 | E4: 42374 | F4: 03-01-2016 | G4: 2 | H4: 7 | J4: {=_xlfn.IFS(C4=4,"Delivered",C4=3,"Shipped",C4=2,"Pending",C4=1,"Ordered")} -> Delivered
A5: 4 | B5: 175 | C5: 4 | D5: 42372 | E5: 42373 | F5: 05-01-2016 | G5: 1 | H5: 3 | J5: {=_xlfn.IFS(C5=4,"Delivered",C5=3,"Shipped",C5=2,"Pending",C5=1,"Ordered")} -> Delivered
A6: 5 | B6: 1324 | C6: 4 | D6: 42372 | E6: 42375 | F6: 06-01-2016 | G6: 2 | H6: 6 | J6: {=_xlfn.IFS(C6=4,"Delivered",C6=3,"Shipped",C6=2,"Pending",C6=1,"Ordered")} -> Delivered
A7: 6 | B7: 94 | C7: 4 | D7: 42373 | E7: 42376 | F7: 05-01-2016 | G7: 2 | H7: 6 | J7: {=_xlfn.IFS(C7=4,"Delivered",C7=3,"Shipped",C7=2,"Pending",C7=1,"Ordered")} -> Delivered
A8: 7 | B8: 324 | C8: 4 | D8: 42373 | E8: 42376 | F8: 05-01-2016 | G8: 2 | H8: 6 | J8: {=_xlfn.IFS(C8=4,"Delivered",C8=3,"Shipped",C8=2,"Pending",C8=1,"Ordered")} -> Delivered
A9: 8 | B9: 1204 | C9: 4 | D9: 42373 | E9: 42374 | F9: 05-01-2016 | G9: 2 | H9: 7 | J9: {=_xlfn.IFS(C9=4,"Delivered",C9=3,"Shipped",C9=2,"Pending",C9=1,"Ordered")} -> Delivered
A10: 9 | B10: 60 | C10: 4 | D10: 42374 | E10: 42377 | F10: 08-01-2016 | G10: 1 | H10: 2 | J10: {=_xlfn.IFS(C10=4,"Delivered",C10=3,"Shipped",C10=2,"Pending",C10=1,"Ordered")} -> Delivered
A11: 10 | B11: 442 | C11: 4 | D11: 42374 | E11: 42375 | F11: 06-01-2016 | G11: 2 | H11: 6 | J11: {=_xlfn.IFS(C11=4,"Delivered",C11=3,"Shipped",C11=2,"Pending",C11=1,"Ordered")} -> Delivered
A12: 11 | B12: 1326 | C12: 4 | D12: 42374 | E12: 42377 | F12: 07-01-2016 | G12: 2 | H12: 7 | J12: {=_xlfn.IFS(C12=4,"Delivered",C12=3,"Shipped",C12=2,"Pending",C12=1,"Ordered")} -> Delivered
A13: 12 | B13: 91 | C13: 4 | D13: 42375 | E13: 42377 | F13: 09-01-2016 | G13: 1 | H13: 2 | J13: {=_xlfn.IFS(C13=4,"Delivered",C13=3,"Shipped",C13=2,"Pending",C13=1,"Ordered")} -> Delivered
... A1616: 1615 | B1616: 136 | C1616: 3 | D1616: 43462 | E1616: 43462 | F1616: NULL | G1616: 3 | H1616: 8 | J1616: {=_xlfn.IFS(C1616=4,"Delivered",C1616=3,"Shipped",C1616=2,"Pending",C1616=1,"Ordered")} -> Shipped

Sheet order_items
A1: Order_id | B1: Item_id | C1: Product_id | D1: Quantity | E1: List_price | F1: Discount | G1: Total_price
A2: 1 | B2: 1 | C2: 20 | D2: 1 | E2: 599.99 | F2: 0.2 | G2: 599.99
A3: 1 | B3: 2 | C3: 8 | D3: 2 | E3: 1799.99 | F3: 0.07 | G3: 3599.98
A4: 1 | B4: 3 | C4: 10 | D4: 2 | E4: 1549 | F4: 0.05 | G4: 3098
A5: 1 | B5: 4 | C5: 16 | D5: 2 | E5: 599.99 | F5: 0.05 | G5: 1199.98
A6: 1 | B6: 5 | C6: 4 | D6: 1 | E6: 2899.99 | F6: 0.2 | G6: 2899.99
A7: 2 | B7: 1 | C7: 20 | D7: 1 | E7: 599.99 | F7: 0.07 | G7: 599.99
A8: 2 | B8: 2 | C8: 16 | D8: 2 | E8: 599.99 | F8: 0.05 | G8: 1199.98
A9: 3 | B9: 1 | C9: 3 | D9: 1 | E9: 999.99 | F9: 0.05 | G9: 999.99
A10: 3 | B10: 2 | C10: 20 | D10: 1 | E10: 599.99 | F10: 0.05 | G10: 599.99
A11: 4 | B11: 1 | C11: 2 | D11: 2 | E11: 749.99 | F11: 0.1 | G11: 1499.98
A12: 5 | B12: 1 | C12: 10 | D12: 2 | E12: 1549 | F12: 0.05 | G12: 3098
A13: 5 | B13: 2 | C13: 17 | D13: 1 | E13: 429 | F13: 0.07 | G13: 429
... A4723: 1615 | B4723: 3 | C4723: 182 | D4723: 1 | E4723: 2499.99 | F4723: 0.2 | G4723: 2499.99

Sheet categories
A1: Category_id | B1: Category_name
A2: 1 | B2: Children Bicycles
A3: 2 | B3: Comfort Bicycles
A4: 3 | B4: Cruisers Bicycles
A5: 4 | B5: Cyclocross Bicycles
A6: 5 | B6: Electric Bikes
A7: 6 | B7: Mountain Bikes
A8: 7 | B8: Road Bikes

Sheet brands
A1: Brand_id | B1: Brand_name
A2: 1 | B2: Electra
A3: 2 | B3: Haro
A4: 3 | B4: Heller
A5: 4 | B5: Pure Cycles
A6: 5 | B6: Ritchey
A7: 6 | B7: Strider
A8: 7 | B8: Sun Bicycles
A9: 8 | B9: Surly
A10: 9 | B10: Trek

Sheet Task 7
A1: Order_id | B1: Item_id | C1: Product_id | D1: Quantity | E1: List_price | F1: Discount | G1: Total_price | I1: Product Name
A2: 1 | B2: 1 | C2: 20 | D2: 1 | E2: 599.99 | F2: 0.2 | G2: 599.99 | I2: =VLOOKUP($C2,products!$A$1:$F$321,2,FALSE) -> Electra Townie Original 7D EQ - Women's - 2016
A3: 1 | B3: 2 | C3: 8 | D3: 2 | E3: 1799.99 | F3: 0.07 | G3: 3599.98 | I3: =VLOOKUP($C3,products!$A$1:$F$321,2,FALSE) -> Trek Remedy 29 Carbon Frameset - 2016
A4: 1 | B4: 3 | C4: 10 | D4: 2 | E4: 1549 | F4: 0.05 | G4: 3098 | I4: =VLOOKUP($C4,products!$A$1:$F$321,2,FALSE) -> Surly Straggler - 2016
A5: 1 | B5: 4 | C5: 16 | D5: 2 | E5: 599.99 | F5: 0.05 | G5: 1199.98 | I5: =VLOOKUP($C5,products!$A$1:$F$321,2,FALSE) -> Electra Townie Original 7D EQ - 2016
A6: 1 | B6: 5 | C6: 4 | D6: 1 | E6: 2899.99 | F6: 0.2 | G6: 2899.99 | I6: =VLOOKUP($C6,products!$A$1:$F$321,2,FALSE) -> Trek Fuel EX 8 29 - 2016
A7: 2 | B7: 1 | C7: 20 | D7: 1 | E7: 599.99 | F7: 0.07 | G7: 599.99 | I7: =VLOOKUP($C7,products!$A$1:$F$321,2,FALSE) -> Electra Townie Original 7D EQ - Women's - 2016
A8: 2 | B8: 2 | C8: 16 | D8: 2 | E8: 599.99 | F8: 0.05 | G8: 1199.98 | I8: =VLOOKUP($C8,products!$A$1:$F$321,2,FALSE) -> Electra Townie Original 7D EQ - 2016
A9: 3 | B9: 1 | C9: 3 | D9: 1 | E9: 999.99 | F9: 0.05 | G9: 999.99 | I9: =VLOOKUP($C9,products!$A$1:$F$321,2,FALSE) -> Surly Wednesday Frameset - 2016
A10: 3 | B10: 2 | C10: 20 | D10: 1 | E10: 599.99 | F10: 0.05 | G10: 599.99 | I10: =VLOOKUP($C10,products!$A$1:$F$321,2,FALSE) -> Electra Townie Original 7D EQ - Women's - 2016
A11: 4 | B11: 1 | C11: 2 | D11: 2 | E11: 749.99 | F11: 0.1 | G11: 1499.98 | I11: =VLOOKUP($C11,products!$A$1:$F$321,2,FALSE) -> Ritchey Timberwolf Frameset - 2016
A12: 5 | B12: 1 | C12: 10 | D12: 2 | E12: 1549 | F12: 0.05 | G12: 3098 | I12: =VLOOKUP($C12,products!$A$1:$F$321,2,FALSE) -> Surly Straggler - 2016
A13: 5 | B13: 2 | C13: 17 | D13: 1 | E13: 429 | F13: 0.07 | G13: 429 | I13: =VLOOKUP($C13,products!$A$1:$F$321,2,FALSE) -> Pure Cycles Vine 8-Speed - 2016
... A4723: 1615 | B4723: 3 | C4723: 182 | D4723: 1 | E4723: 2499.99 | F4723: 0.2 | G4723: 2499.99 | I4723: =VLOOKUP($C4723,products!$A$1:$F$321,2,FALSE) -> Trek Domane SL 5 Disc - 2018

Sheet Task8
A1: Row Labels | B1: Sum of List_price
A2: Children Bicycles | B2: 16979.41
A3: Comfort Bicycles | B3: 20463.7
A4: Cruisers Bicycles | B4: 56972.16
A5: Cyclocross Bicycles | B5: 25427.93
A6: Electric Bikes | B6: 78759.76
A7: Mountain Bikes | B7: 98985.44
A8: Road Bikes | B8: 190521.44
A9: Grand Total | B9: 488109.84

Sheet Task9
A1: Product_id | B1: Product_name | C1: Brand_id | D1: Category_id | E1: Model_year | F1: List_price
A2: 1 | B2: Trek 820 - 2016 | C2: 9 | D2: 6 | E2: 2016 | F2: 379.99
A3: 2 | B3: Ritchey Timberwolf Frameset - 2016 | C3: 5 | D3: 6 | E3: 2016 | F3: 749.99
A4: 3 | B4: Surly Wednesday Frameset - 2016 | C4: 8 | D4: 6 | E4: 2016 | F4: 999.99
A5: 4 | B5: Trek Fuel EX 8 29 - 2016 | C5: 9 | D5: 6 | E5: 2016 | F5: 2899.99
A6: 5 | B6: Heller Shagamaw Frame - 2016 | C6: 3 | D6: 6 | E6: 2016 | F6: 1320.99
A7: 6 | B7: Surly Ice Cream Truck Frameset - 2016 | C7: 8 | D7: 6 | E7: 2016 | F7: 469.99
A8: 7 | B8: Trek Slash 8 27.5 - 2016 | C8: 9 | D8: 6 | E8: 2016 | F8: 3999.99
A9: 8 | B9: Trek Remedy 29 Carbon Frameset - 2016 | C9: 9 | D9: 6 | E9: 2016 | F9: 1799.99
A10: 9 | B10: Trek Conduit+ - 2016 | C10: 9 | D10: 5 | E10: 2016 | F10: 2999.99
A11: 10 | B11: Surly Straggler - 2016 | C11: 8 | D11: 4 | E11: 2016 | F11: 1549
A12: 11 | B12: Surly Straggler 650b - 2016 | C12: 8 | D12: 4 | E12: 2016 | F12: 1680.99
A13: 12 | B13: Electra Townie Original 21D - 2016 | C13: 1 | D13: 3 | E13: 2016 | F13: 549.99
... A322: 321 | B322: Trek Checkpoint ALR Frameset - 2019 | C322: 9 | D322: 7 | E322: 2019 | F322: 3199.99
